MANIFEST.in
README.rst
setup.cfg
setup.py
pylexicon/__init__.py
pylexicon/core.py
pylexicon/testPyLexicon.py
pylexicon.egg-info/PKG-INFO
pylexicon.egg-info/SOURCES.txt
pylexicon.egg-info/dependency_links.txt
pylexicon.egg-info/requires.txt
pylexicon.egg-info/top_level.txt