Metadata-Version: 1.1
Name: pylexicon
Version: 1.0.4
Summary: A python module to get meanings, synonyms and antonyms of words
Home-page: http://github.com/LordFlashmeow/pylexicon
Author: LordFlashmeow
Author-email: dash098@gmail.com
License: MIT
Keywords: dictionary lexicon define meaning synonym antonym
Platform: UNKNOWN
Classifier: Development Status :: 5 - Production/Stable
Classifier: Intended Audience :: Developers
